{
  "coffees": [
    {
      "id": 1,
      "name": "Эспрессо",
      "type": "кофе",
      "price": 200,
      "quantity": 42,
      "description": "Классический крепкий кофе, приготовленный под высоким давлением. Идеальный вариант для настоящих ценителей.",
      "icon": "fas fa-coffee",
      "image": "https://chillesta.ru/wp-content/uploads/2025/06/cup-coffee-with-word-latte-it.jpg"
    },
    {
      "id": 2,
      "name": "Капучино",
      "type": "кофе",
      "price": 280,
      "quantity": 42,
      "description": "Идеальное сочетание эспрессо, горячего молока и молочной пенки. Нежный и воздушный напиток.",
      "icon": "fas fa-mug-hot",
      "image": "https://s11.stc.all.kpcdn.net/family/wp-content/uploads/2025/11/8-luchshih-reczeptov-kofe-kapuchino-osnovnoe-foto.jpg"
    },
    {
      "id": 3,
      "name": "Латте",
      "type": "кофе",
      "price": 320,
      "quantity": 40,
      "description": "Мягкий кофейный напиток на основе эспрессо с большим количеством молока и нежной пенкой.",
      "icon": "fas fa-coffee",
      "image": "https://stockmeier-food.ru/uploads/posts/2021-11/1636961735_aromatizator-kofe-latte.jpg"
    },
    {
      "id": 4,
      "name": "Американо",
      "type": "кофе",
      "price": 220,
      "quantity": 55,
      "description": "Эспрессо, разбавленный горячей водой. Идеальный выбор для тех, кто предпочитает менее крепкий кофе.",
      "icon": "fas fa-mug-hot",
      "image": "https://i.pinimg.com/originals/51/3c/aa/513caaee093ae4e2af2e41135082c9a6.jpg"
    },
    {
      "id": 5,
      "name": "Чизкейк Нью-Йорк",
      "type": "десерт",
      "price": 350,
      "quantity": 15,
      "description": "Классический нью-йоркский чизкейк с нежной творожной основой и ягодным соусом.",
      "icon": "fas fa-cheese",
      "image": "https://crazybrothers.ru/wp-content/uploads/Chizkejk-Nju-Jork-1.jpg"
    },
    {
      "id": 6,
      "name": "Круассан",
      "type": "выпечка",
      "price": 180,
      "quantity": 26,
      "description": "Свежий слоеный круассан с хрустящей корочкой и нежной масляной текстурой.",
      "icon": "fas fa-bread-slice",
      "image": "https://img-s-msn-com.akamaized.net/tenant/amp/entityid/AA1FVnQZ.img?w=1000&h=564&m=4&q=31"
    },
    {
      "id": 7,
      "name": "Зеленый чай с жасмином",
      "type": "чай",
      "price": 350,
      "quantity": 40,
      "description": "Ароматный зеленый чай с цветами жасмина. Освежающий и тонизирующий напиток.",
      "icon": "fas fa-leaf",
      "image": "https://avatars.mds.yandex.net/get-mpic/4012682/img_id5901137050384813470.png/orig"
    },
    {
      "id": 8,
      "name": "Горячий шоколад",
      "type": "напиток",
      "price": 300,
      "quantity": 35,
      "description": "Густой горячий шоколад с взбитыми сливками и тертым шоколадом. Идеальный напиток для холодного дня.",
      "icon": "fas fa-hot-chocolate",
      "image": "https://s.yimg.com/ny/api/res/1.2/9_kLUZIKQmQqFyMbEX00dg--/YXBwaWQ9aGlnaGxhbmRlcjt3PTEyMDA7aD02NzU7Y2Y9d2VicA--/https://media.zenfs.com/en-US/homerun/delish_597/010b6306e9d57092c78d399ac5780672"
    }
  ],
  "users": [
    {
      "id": 1,
      "name": "Администратор",
      "email": "admin@cozycup.ru",
      "password": "admin123",
      "isAdmin": true,
      "loyaltyPoints": 0,
      "joinDate": "2023-01-01T00:00:00.000Z"
    },
    {
      "id": 2,
      "name": "Иван Петров",
      "email": "ivan@example.com",
      "password": "user123",
      "isAdmin": false,
      "loyaltyPoints": 150,
      "joinDate": "2023-05-15T10:30:00.000Z"
    },
    {
      "id": 3,
      "name": "Мария Сидорова",
      "email": "maria@example.com",
      "password": "user123",
      "isAdmin": false,
      "loyaltyPoints": 420,
      "joinDate": "2023-06-20T14:45:00.000Z"
    },
    {
      "id": 4,
      "name": "Екатерина ",
      "email": "ek@yandex.ru",
      "password": "qwe123",
      "isAdmin": false,
      "loyaltyPoints": 40,
      "joinDate": "2025-12-17T19:50:24.002Z"
    },
    {
      "id": 5,
      "name": "Егор",
      "email": "eg@yandex.ru",
      "password": "qwe123",
      "isAdmin": false,
      "loyaltyPoints": 40,
      "joinDate": "2025-12-17T19:51:29.989Z"
    },
    {
      "id": 6,
      "name": "Настя",
      "email": "nast@yandex.ru",
      "password": "qwe123",
      "isAdmin": false,
      "loyaltyPoints": 35,
      "joinDate": "2025-12-17T19:51:45.176Z"
    },
    {
      "id": 7,
      "name": "Олег",
      "email": "oleg@yandex.ru",
      "password": "qwe123",
      "isAdmin": false,
      "loyaltyPoints": 40,
      "joinDate": "2025-12-17T19:52:11.484Z"
    }
  ],
  "orders": [
    {
      "id": 1,
      "userId": 2,
      "items": [
        {
          "id": 1,
          "name": "Эспрессо",
          "price": 200,
          "quantity": 2
        },
        {
          "id": 5,
          "name": "Чизкейк Нью-Йорк",
          "price": 350,
          "quantity": 1
        }
      ],
      "total": 750,
      "pointsEarned": 37,
      "date": "2023-10-05T12:30:00.000Z",
      "status": "completed"
    },
    {
      "id": 2,
      "userId": 3,
      "items": [
        {
          "id": 3,
          "name": "Латте",
          "price": 320,
          "quantity": 1
        },
        {
          "id": 6,
          "name": "Круассан",
          "price": 180,
          "quantity": 2
        }
      ],
      "total": 680,
      "pointsEarned": 34,
      "date": "2023-10-10T15:45:00.000Z",
      "status": "completed"
    },
    {
      "id": 3,
      "userId": 2,
      "items": [
        {
          "id": 2,
          "name": "Капучино",
          "price": 280,
          "quantity": 3
        },
        {
          "id": 8,
          "name": "Горячий шоколад",
          "price": 300,
          "quantity": 1
        }
      ],
      "total": 1140,
      "pointsEarned": 57,
      "date": "2023-10-15T09:20:00.000Z",
      "status": "completed"
    },
    {
      "id": 4,
      "userId": 4,
      "items": [
        {
          "id": 2,
          "name": "Капучино",
          "price": 280,
          "quantity": 3,
          "icon": "fas fa-mug-hot"
        }
      ],
      "total": 840,
      "pointsEarned": 40,
      "date": "2025-12-17T19:50:28.145Z",
      "status": "completed"
    },
    {
      "id": 5,
      "userId": 5,
      "items": [
        {
          "id": 1,
          "name": "Эспрессо",
          "price": 200,
          "quantity": 4,
          "icon": "fas fa-coffee"
        }
      ],
      "total": 800,
      "pointsEarned": 40,
      "date": "2025-12-17T19:51:33.307Z",
      "status": "completed"
    },
    {
      "id": 6,
      "userId": 6,
      "items": [
        {
          "id": 6,
          "name": "Круассан",
          "price": 180,
          "quantity": 4,
          "icon": "fas fa-bread-slice"
        }
      ],
      "total": 720,
      "pointsEarned": 35,
      "date": "2025-12-17T19:51:52.138Z",
      "status": "completed"
    },
    {
      "id": 7,
      "userId": 7,
      "items": [
        {
          "id": 1,
          "name": "Эспрессо",
          "price": 200,
          "quantity": 4,
          "icon": "fas fa-coffee"
        }
      ],
      "total": 800,
      "pointsEarned": 40,
      "date": "2025-12-17T19:52:14.980Z",
      "status": "completed"
    }
  ],
  "loyaltySettings": {
    "pointsPerPurchase": 5,
    "levels": [
      {
        "points": 0,
        "name": "Новичок",
        "discount": 0,
        "className": "level-beginner"
      },
      {
        "points": 100,
        "name": "Постоянный клиент",
        "discount": 5,
        "className": "level-regular"
      },
      {
        "points": 300,
        "name": "Любитель кофе",
        "discount": 10,
        "className": "level-enthusiast"
      },
      {
        "points": 600,
        "name": "Кофейный эксперт",
        "discount": 15,
        "className": "level-expert"
      },
      {
        "points": 1000,
        "name": "Кофейный гурман",
        "discount": 20,
        "className": "level-master"
      }
    ]
  }
}
